pywatemsedem/__init__.py
pywatemsedem/buffers.py
pywatemsedem/calibrate.py
pywatemsedem/catchment.py
pywatemsedem/cfactor.py
pywatemsedem/cn.py
pywatemsedem/compare_scenario.py
pywatemsedem/defaults.py
pywatemsedem/errors.py
pywatemsedem/grasstrips.py
pywatemsedem/ktc.py
pywatemsedem/parcelslanduse.py
pywatemsedem/plots.py
pywatemsedem/postprocess.py
pywatemsedem/scenario.py
pywatemsedem/templates.py
pywatemsedem/testing.py
pywatemsedem/tools.py
pywatemsedem/userchoices.py
pywatemsedem/valid.py
pywatemsedem/data/.~lock.filestructure_cnws_python.csv#
pywatemsedem/data/CN_table.csv
pywatemsedem/data/example_calibration_data.csv
pywatemsedem/data/postprocess_files.csv
pywatemsedem/geo/__init__.py
pywatemsedem/geo/factory.py
pywatemsedem/geo/rasterproperties.py
pywatemsedem/geo/rasters.py
pywatemsedem/geo/utils.py
pywatemsedem/geo/valid.py
pywatemsedem/geo/vectors.py
pywatemsedem/io/__init__.py
pywatemsedem/io/folders.py
pywatemsedem/io/ini.py
pywatemsedem/io/modelinput.py
pywatemsedem/io/modeloutput.py
pywatemsedem/io/plots.py
pywatemsedem/io/valid.py
pywatemsedem-0.0.1a9.dist-info/AUTHORS.rst
pywatemsedem-0.0.1a9.dist-info/LICENSE.txt
pywatemsedem-0.0.1a9.dist-info/METADATA
pywatemsedem-0.0.1a9.dist-info/WHEEL
pywatemsedem-0.0.1a9.dist-info/top_level.txt
pywatemsedem-0.0.1a9.dist-info/RECORD
