Metadata-Version: 2.1
Name: pywatemsedem
Version: 0.0.1a9
Summary: Python Wrapper for WaTEM/SEDEM
Author: Sacha Gobeyn
Author-email: sacha@fluves.com
License: MIT
Platform: any
Classifier: Development Status :: 4 - Beta
Classifier: Programming Language :: Python
Classifier: Programming Language :: Python :: 3.9
Classifier: Programming Language :: Python :: 3.10
Classifier: Programming Language :: Python :: 3.11
Classifier: Programming Language :: Python :: 3.12
Classifier: Intended Audience :: Science/Research
Classifier: Natural Language :: English
Classifier: Topic :: Scientific/Engineering
Classifier: Topic :: Scientific/Engineering :: Physics
Requires-Python: >=3.9
License-File: LICENSE.txt
License-File: AUTHORS.rst
Requires-Dist: jupyter
Requires-Dist: geopandas
Requires-Dist: fiona
Requires-Dist: rasterio
Requires-Dist: xlrd
Requires-Dist: matplotlib
Requires-Dist: openpyxl
Requires-Dist: scikit-learn
Requires-Dist: python-dotenv
Requires-Dist: pandoc
Provides-Extra: develop
Requires-Dist: black; extra == "develop"
Requires-Dist: configupdater; extra == "develop"
Requires-Dist: flake8; extra == "develop"
Requires-Dist: interrogate; extra == "develop"
Requires-Dist: nbsphinx; extra == "develop"
Requires-Dist: nbstripout; extra == "develop"
Requires-Dist: pre-commit; extra == "develop"
Requires-Dist: pyscaffold; extra == "develop"
Requires-Dist: pytest; extra == "develop"
Requires-Dist: python-dotenv; extra == "develop"
Requires-Dist: pytest-cov; extra == "develop"
Requires-Dist: pytest-datafiles; extra == "develop"
Requires-Dist: pytest-xdist; extra == "develop"
Requires-Dist: setuptools_scm; extra == "develop"
Requires-Dist: sphinx; extra == "develop"
Requires-Dist: sphinx-copybutton; extra == "develop"
Requires-Dist: sphinx_rtd_theme; extra == "develop"
Requires-Dist: tox; extra == "develop"
Requires-Dist: virtualenv; extra == "develop"
